konf/__init__.py
konf/main.py
konf/examples/__init__.py
konf/examples/example.py
konf/examples/example1.py
konf/testing/__init__.py
konf/testing/tests.py
konf/testing/assets/1.json
konf/testing/assets/1.yml
konf/testing/assets/2.yml
konf/testing/assets/3.yml
konf/testing/assets/4.yml
konf/testing/assets/5.yml
konf/testing/assets/6.yml
konf/testing/assets/bad.json
konf-1.2.dist-info/DESCRIPTION.rst
konf-1.2.dist-info/METADATA
konf-1.2.dist-info/metadata.json
konf-1.2.dist-info/RECORD
konf-1.2.dist-info/top_level.txt
konf-1.2.dist-info/WHEEL
