Metadata-Version: 2.0
Name: konf
Version: 1.2
Summary: Konf is a Python package which designed to simplify the use of variables in configuration files. json and yaml supported out of the box. 
Home-page: http://github.com/vartagg/konf/
Author: Vladimir Chub
Author-email: vartagg@users.noreply.github.com
License: BSD
Keywords: konf,json,yaml,config
Platform: UNKNOWN
Classifier: Development Status :: 5 - Production/Stable
Classifier: Intended Audience :: Developers
Classifier: Intended Audience :: System Administrators
Classifier: License :: OSI Approved :: BSD License
Classifier: Programming Language :: Python :: 2.7
Classifier: Programming Language :: Python :: 3.3
Classifier: Programming Language :: Python :: 3.4
Classifier: Programming Language :: Python :: 3.5
Requires-Dist: PyYAML
Requires-Dist: good
